m3u8dwn/__init__.py
m3u8dwn/boot.py
m3u8dwn/down.py
m3u8dwn-1.0.1.dist-info/METADATA
m3u8dwn-1.0.1.dist-info/WHEEL
m3u8dwn-1.0.1.dist-info/entry_points.txt
m3u8dwn-1.0.1.dist-info/top_level.txt
m3u8dwn-1.0.1.dist-info/RECORD
