Metadata-Version: 2.1
Name: m3u8dwn
Version: 1.0.1
Summary: m3u8dwn: fast way to download m3u8 video
Home-page: https://github.com/shigebeyond/m3u8dwn
Author: shigebeyond
Author-email: 772910474@qq.com
License: BSD
Classifier: Development Status :: 5 - Production/Stable
Classifier: Topic :: Software Development :: Libraries :: Python Modules
Classifier: Operating System :: POSIX :: Linux
Classifier: Operating System :: MacOS :: MacOS X
Classifier: Operating System :: Microsoft :: Windows
Classifier: Programming Language :: Python
Classifier: Programming Language :: Python :: 3.7
Classifier: Programming Language :: Python :: 3.8
Classifier: Programming Language :: Python :: 3.9
Requires-Python: >=3.6
Requires-Dist: pyutilb (>=1.0.5)
Requires-Dist: m3u8 (>=3.3.0)
Requires-Dist: pycrypto (>=2.6.1)
Requires-Dist: httpx (>=0.23.3)
